density_aware_smote/evaluation.py
density_aware_smote/main.py
density_aware_smote/smote.py
density_aware_smote/utils.py
density_aware_smote/visualizations.py
density_aware_smote-0.1.0.dist-info/licenses/LICENSE.txt
density_aware_smote-0.1.0.dist-info/METADATA
density_aware_smote-0.1.0.dist-info/WHEEL
density_aware_smote-0.1.0.dist-info/top_level.txt
density_aware_smote-0.1.0.dist-info/RECORD
