Metadata-Version: 2.4
Name: density-aware-smote
Version: 0.1.0
Summary: Density Aware SMOTE: A Python package for density-aware synthetic oversampling
Author-email: Your Name <your.email@example.com>
Project-URL: Homepage, https://github.com/nbeeeel/Improved-Oversampling-Density-Aware-Smote
Project-URL: Bug Tracker, https://github.com/nbeeeel/Improved-Oversampling-Density-Aware-Smote/issues
Keywords: SMOTE,oversampling,machine-learning,imbalanced-data,synthetic-data
Classifier: Development Status :: 3 - Alpha
Classifier: Intended Audience :: Science/Research
Classifier: License :: OSI Approved :: MIT License
Classifier: Programming Language :: Python :: 3
Classifier: Programming Language :: Python :: 3.8
Classifier: Programming Language :: Python :: 3.9
Classifier: Programming Language :: Python :: 3.10
Classifier: Topic :: Scientific/Engineering :: Artificial Intelligence
Requires-Python: >=3.7
License-File: LICENSE.txt
Requires-Dist: numpy
Requires-Dist: scikit-learn
Requires-Dist: matplotlib
Dynamic: license-file
